{
  "success": true,
  "desc": null,
  "data": {
    "list": [
      {
        "launchCount": 100,
        "clickCount": 100,
        "clickRate": 1,
        "adConcume": 100,
        "orderCount": 100,
        "orderRate": 1,
        "cpa": 1,
        "issueCount": 100,
        "issueRate": 1,
        "successCt": 100,
        "successRate": 1,
        "onedaySuccessRate": 1,
        "threedaySuccessRate": 1,
        "fivedaySuccessRate": 1,
        "otherSuccessRate": 1,
        "id": 1002,
        "name": "测试app0",
        "times": null,
        "arpu": 1,
        "keepSuccessRate": 0.1,
        "itemRoi": 0.1,
        "orderCompleteRate": 0.1235
      },
      {
        "launchCount": 200,
        "clickCount": 200,
        "clickRate": 1,
        "adConcume": 200,
        "orderCount": 200,
        "orderRate": 1,
        "cpa": 1,
        "issueCount": 200,
        "issueRate": 1,
        "successCt": 200,
        "successRate": 1,
        "onedaySuccessRate": 1,
        "threedaySuccessRate": 1,
        "fivedaySuccessRate": 1,
        "otherSuccessRate": 1,
        "id": 2002,
        "name": "测试app0",
        "times": null,
        "arpu": 1,
        "keepSuccessRate": 0.1,
        "itemRoi": 0.1,
        "orderCompleteRate": 0.1235
      },
      {
        "launchCount": 300,
        "clickCount": 300,
        "clickRate": 1,
        "adConcume": 300,
        "orderCount": 300,
        "orderRate": 1,
        "cpa": 1,
        "issueCount": 300,
        "issueRate": 1,
        "successCt": 300,
        "successRate": 1,
        "onedaySuccessRate": 1,
        "threedaySuccessRate": 1,
        "fivedaySuccessRate": 1,
        "otherSuccessRate": 1,
        "id": 2005,
        "name": "测试app2",
        "times": null,
        "arpu": 1,
        "keepSuccessRate": 0.1,
        "itemRoi": 0.1,
        "orderCompleteRate": 0.1235
      },
      {
        "launchCount": 300,
        "clickCount": 300,
        "clickRate": 1,
        "adConcume": 300,
        "orderCount": 300,
        "orderRate": 1,
        "cpa": 1,
        "issueCount": 300,
        "issueRate": 1,
        "successCt": 300,
        "successRate": 1,
        "onedaySuccessRate": 1,
        "threedaySuccessRate": 1,
        "fivedaySuccessRate": 1,
        "otherSuccessRate": 1,
        "id": 2007,
        "name": "测试app5",
        "times": null,
        "arpu": 1,
        "keepSuccessRate": 0.1,
        "itemRoi": 0.1,
        "orderCompleteRate": 0.1235
      },
      {
        "launchCount": 200,
        "clickCount": 200,
        "clickRate": 1,
        "adConcume": 200,
        "orderCount": 200,
        "orderRate": 1,
        "cpa": 1,
        "issueCount": 200,
        "issueRate": 1,
        "successCt": 200,
        "successRate": 1,
        "onedaySuccessRate": 1,
        "threedaySuccessRate": 1,
        "fivedaySuccessRate": 1,
        "otherSuccessRate": 1,
        "id": 2010,
        "name": "测试app8",
        "times": null,
        "arpu": 1,
        "keepSuccessRate": 0.1,
        "itemRoi": 0.1,
        "orderCompleteRate": 0.1235
      }
    ],
    "count": 5
  }
}